pelican/plugins/css_cache_bust/__init__.py
pelican/plugins/css_cache_bust/css_cache_bust.py
pelican/plugins/css_cache_bust/test_css_cache_bust.py
pelican_css_cache_bust-0.2.0.dist-info/AUTHORS
pelican_css_cache_bust-0.2.0.dist-info/LICENSE
pelican_css_cache_bust-0.2.0.dist-info/METADATA
pelican_css_cache_bust-0.2.0.dist-info/WHEEL
pelican_css_cache_bust-0.2.0.dist-info/top_level.txt
pelican_css_cache_bust-0.2.0.dist-info/RECORD
