Metadata-Version: 2.1
Name: pelican-css-cache-bust
Version: 0.2.0
Summary: Calculate a CSS_FILE_CACHE_BUST value to use as cache bust query strings
Author-email: Diego Escalante Urrelo <diegoe@gnome.org>
Maintainer-email: Diego Escalante Urrelo <diegoe@gnome.org>
Project-URL: Homepage, https://github.com/diegoe/pelican-css-cache-bust
Project-URL: Issues, https://github.com/diegoe/pelican-css-cache-bust/issues
Project-URL: Repository, https://github.com/diegoe/pelican-css-cache-bust.git
Classifier: Development Status :: 4 - Beta
Classifier: Environment :: Console
Classifier: Environment :: Plugins
Classifier: Framework :: Pelican
Classifier: Framework :: Pelican :: Plugins
Classifier: Intended Audience :: End Users/Desktop
Classifier: License :: OSI Approved :: GNU Affero General Public License v3
Classifier: Operating System :: OS Independent
Classifier: Programming Language :: Python
Classifier: Programming Language :: Python :: 3.12
Classifier: Topic :: Communications
Classifier: Topic :: Internet :: WWW/HTTP :: Site Management
Classifier: Topic :: Software Development :: Libraries :: Python Modules
Classifier: Topic :: Utilities
Requires-Python: >=3.12
License-File: LICENSE
License-File: AUTHORS
Requires-Dist: pelican
Provides-Extra: dev
Requires-Dist: black ; extra == 'dev'
Requires-Dist: build ; extra == 'dev'
Requires-Dist: flake8 ; extra == 'dev'
Requires-Dist: flake8-docstrings ; extra == 'dev'
Requires-Dist: flake8-import-order ; extra == 'dev'
Requires-Dist: pytest ; extra == 'dev'
